[
  {
    "title": "Death Note Anime_L1",
    "link_thumb": "https://live.staticflickr.com/65535/51787561499_e3dba368d4_o.gif",
    "id_album": "-374116174",
    "total": 8,
    "size_max_detail_page": 1,
    "list_detail": [
      {
        "index_page": 0,
        "link_page": "https://github.com/lmbstudiocontact/mb4_dt_alb_0/raw/main/14132021_dta_-374116174_index_0.json"
      }
    ]
  },
  {
    "title": "Cute Art_L8",
    "link_thumb": "https://live.staticflickr.com/65535/51787561349_85c85e2afd_o.gif",
    "id_album": "-629963483",
    "total": 76,
    "size_max_detail_page": 2,
    "list_detail": [
      {
        "index_page": 0,
        "link_page": "https://github.com/lmbstudiocontact/mb4_dt_alb_0/raw/main/14132021_dta_-629963483_index_0.json"
      },
      {
        "index_page": 1,
        "link_page": "https://github.com/lmbstudiocontact/mb4_dt_alb_0/raw/main/14132021_dta_-629963483_index_1.json"
      }
    ]
  },
  {
    "title": "Couple_L2",
    "link_thumb": "https://live.staticflickr.com/65535/51786098522_53d5c490da_o.gif",
    "id_album": "-888889819",
    "total": 24,
    "size_max_detail_page": 1,
    "list_detail": [
      {
        "index_page": 0,
        "link_page": "https://github.com/lmbstudiocontact/mb4_dt_alb_0/raw/main/14132021_dta_-888889819_index_0.json"
      }
    ]
  },
  {
    "title": "Dragon Art_L3",
    "link_thumb": "https://live.staticflickr.com/65535/51786943826_9f4d460e59_o.gif",
    "id_album": "2059014000",
    "total": 13,
    "size_max_detail_page": 1,
    "list_detail": [
      {
        "index_page": 0,
        "link_page": "https://github.com/lmbstudiocontact/mb4_dt_alb_0/raw/main/14132021_dta_2059014000_index_0.json"
      }
    ]
  },
  {
    "title": "Kitty & My Melody_L5",
    "link_thumb": "https://live.staticflickr.com/65535/51787029276_b790a9e552_o.gif",
    "id_album": "-378480541",
    "total": 76,
    "size_max_detail_page": 2,
    "list_detail": [
      {
        "index_page": 0,
        "link_page": "https://github.com/lmbstudiocontact/mb4_dt_alb_0/raw/main/14132021_dta_-378480541_index_0.json"
      },
      {
        "index_page": 1,
        "link_page": "https://github.com/lmbstudiocontact/mb4_dt_alb_0/raw/main/14132021_dta_-378480541_index_1.json"
      }
    ]
  },
  {
    "title": "Ragnarok_L1",
    "link_thumb": "https://live.staticflickr.com/65535/51787739604_bee4acea07_o.gif",
    "id_album": "1601322209",
    "total": 15,
    "size_max_detail_page": 1,
    "list_detail": [
      {
        "index_page": 0,
        "link_page": "https://github.com/lmbstudiocontact/mb4_dt_alb_0/raw/main/14132021_dta_1601322209_index_0.json"
      }
    ]
  },
  {
    "title": "Panda Art_L8",
    "link_thumb": "https://live.staticflickr.com/65535/51787085816_2d48020bbd_o.gif",
    "id_album": "586574350",
    "total": 5,
    "size_max_detail_page": 1,
    "list_detail": [
      {
        "index_page": 0,
        "link_page": "https://github.com/lmbstudiocontact/mb4_dt_alb_0/raw/main/14132021_dta_586574350_index_0.json"
      }
    ]
  },
  {
    "title": "Ghibli Anime_L8",
    "link_thumb": "https://live.staticflickr.com/65535/51787243948_c8d57ed911_o.gif",
    "id_album": "-749595040",
    "total": 17,
    "size_max_detail_page": 1,
    "list_detail": [
      {
        "index_page": 0,
        "link_page": "https://github.com/lmbstudiocontact/mb4_dt_alb_0/raw/main/14132021_dta_-749595040_index_0.json"
      }
    ]
  },
  {
    "title": "Spider Man Cartoon_L2",
    "link_thumb": "https://live.staticflickr.com/65535/51787128056_cb136ca681_o.gif",
    "id_album": "1735002392",
    "total": 16,
    "size_max_detail_page": 1,
    "list_detail": [
      {
        "index_page": 0,
        "link_page": "https://github.com/lmbstudiocontact/mb4_dt_alb_0/raw/main/14132021_dta_1735002392_index_0.json"
      }
    ]
  },
  {
    "title": "Animal Art_L3",
    "link_thumb": "https://live.staticflickr.com/65535/51787171103_f9015a302c_o.gif",
    "id_album": "97007463",
    "total": 7,
    "size_max_detail_page": 1,
    "list_detail": [
      {
        "index_page": 0,
        "link_page": "https://github.com/lmbstudiocontact/mb4_dt_alb_0/raw/main/14132021_dta_97007463_index_0.json"
      }
    ]
  }
]